pydantic_pony/__init__.py
pydantic_pony/main.py
pydantic_pony-0.0.1.dist-info/LICENSE
pydantic_pony-0.0.1.dist-info/METADATA
pydantic_pony-0.0.1.dist-info/WHEEL
pydantic_pony-0.0.1.dist-info/top_level.txt
pydantic_pony-0.0.1.dist-info/RECORD
